setup.py
asix_DanielSaez/funciones.py
asix_DanielSaez2.egg-info/PKG-INFO
asix_DanielSaez2.egg-info/SOURCES.txt
asix_DanielSaez2.egg-info/dependency_links.txt
asix_DanielSaez2.egg-info/top_level.txt