Metadata-Version: 2.1
Name: asix-DanielSaez2
Version: 0.1
Summary: Un paquete para calcular áreas y longitudes de polígonos
Author: danielsaezpalo
